lunakit/__about__.py
lunakit/__init__.py
lunakit/__main__.py
lunakit/album.py
lunakit/attridict.py
lunakit/cli.py
lunakit/clients.py
lunakit/config.py
lunakit/filtering.py
lunakit/order.py
lunakit/post.py
lunakit/stream.py
lunakit/utils.py
lunakit/data/default_config.ini
lunakit/resources/__init__.py
lunakit/resources/artcom.py
lunakit/resources/base.py
lunakit/resources/info.py
lunakit/resources/media.py
lunakit/resources/notes.py
lunakit-0.4.9.post3.dist-info/METADATA
lunakit-0.4.9.post3.dist-info/RECORD
lunakit-0.4.9.post3.dist-info/WHEEL
lunakit-0.4.9.post3.dist-info/entry_points.txt
lunakit-0.4.9.post3.dist-info/top_level.txt
