Metadata-Version: 2.1
Name: lunakit
Version: 0.4.9.post3
Summary: Obsolete - See https://pypi.org/project/lunafind instead.
Home-page: https://github.com/mirukan/lunafind
Author: miruka
Author-email: miruka@disroot.org
License: LGPLv3
Platform: UNKNOWN
Classifier: Development Status :: 3 - Alpha
Classifier: Intended Audience :: Developers
Classifier: Intended Audience :: End Users/Desktop
Classifier: Environment :: Console
Classifier: Topic :: Utilities
Classifier: Topic :: Internet :: WWW/HTTP :: Indexing/Search
Classifier: Topic :: Software Development :: Libraries :: Python Modules
Classifier: License :: OSI Approved :: GNU Lesser General Public License v3 or later (LGPLv3+)
Classifier: Programming Language :: Python :: 3
Classifier: Programming Language :: Python :: 3 :: Only
Classifier: Programming Language :: Python :: 3.6
Classifier: Programming Language :: Python :: 3.7
Classifier: Natural Language :: English
Classifier: Operating System :: POSIX
Requires-Python: >=3.6, <4
Requires-Dist: appdirs
Requires-Dist: atomicfile
Requires-Dist: blessed
Requires-Dist: cached-property
Requires-Dist: docopt
Requires-Dist: lazy-object-proxy
Requires-Dist: logzero
Requires-Dist: pendulum
Requires-Dist: pybooru
Requires-Dist: pygments
Requires-Dist: requests
Requires-Dist: setuptools
Requires-Dist: simplejson
Requires-Dist: urllib3
Requires-Dist: whratio
Requires-Dist: dataclasses; python_version < "3.7"
